chatsonic/__init__.py
chatsonic/chatsonic.py
chatsonic-0.1.2.dist-info/LICENSE
chatsonic-0.1.2.dist-info/WHEEL
chatsonic-0.1.2.dist-info/METADATA
chatsonic-0.1.2.dist-info/RECORD
