Metadata-Version: 2.1
Name: chatsonic
Version: 0.1.2
Summary: ChatGPT Alternative API with real time superpowers
Author: Gupta-Anubhav12
Author-email: anubhavgupta2260@gmail.com
Requires-Python: >=3.10,<4.0
Classifier: Programming Language :: Python :: 3
Classifier: Programming Language :: Python :: 3.10
Classifier: Programming Language :: Python :: 3.11
Requires-Dist: bumpver (>=2022.1120,<2023.0)
Requires-Dist: twine (>=4.0.2,<5.0.0)
